{
  "general_attributes": {
    "animations": {
      "shoot": "craftingdead:submachine_shoot",
      "reload": "craftingdead:reload",
      "inspect": "craftingdead:inspect"
    },
    "secondary_action_trigger": "toggle",
    "fire_mode": [
      "auto"
    ],
    "accepted_magazines": [
      "craftingdead:mk48mod_magazine"
    ],
    "default_magazine": "craftingdead:mk48mod_magazine",
    "accepted_attachments": [
      "craftingdead:red_dot_sight",
      "craftingdead:eotech_sight",
      "craftingdead:suppressor",
      "craftingdead:bipod",
      "craftingdead:tactical_grip"
    ],
    "recoil": 5.0,
    "range": 260.0,
    "fire_delay": 92,
    "damage": 7,
    "reload_duration": 80,
    "accuracy": 0.79
  },
  "sounds": {
    "reload_sound": "craftingdead:m240b_reload",
    "shoot_sound": "craftingdead:mk48mod_shoot",
    "silenced_shoot_sound": "craftingdead:silenced_mk48mod_shoot"
  },
  "type": "craftingdead:aimable"
}